src/zoo/__init__.py
src/zoo/line_plot.py
src/zoo/para_optimize.py
src/zoo/pre_processing.py
src/zoo/std_acc.py
src/zoo/train_and_predict_model.py
src/zoo/zoo.py
dsci310_g7_zoo-1.0.1.dist-info/LICENSE
dsci310_g7_zoo-1.0.1.dist-info/WHEEL
dsci310_g7_zoo-1.0.1.dist-info/METADATA
dsci310_g7_zoo-1.0.1.dist-info/RECORD
